{"name":"build-javascript","namedChunkGroups":{"app":{"name":"app","assets":[{"name":"webpack-runtime-70c10d1287d3421d6317.js","size":4794},{"name":"framework-106eaf75e588fec2b76f.js","size":140769},{"name":"app-471009a47af3571792ef.js","size":67714}],"filteredAssets":0,"assetsSize":213277,"filteredAuxiliaryAssets":3,"auxiliaryAssetsSize":611942},"component---src-pages-index-js":{"name":"component---src-pages-index-js","assets":[{"name":"styles.61e7f43be944aab70bb1.css","size":27233},{"name":"component---src-pages-index-js-6ea60e05fc2bfc306125.js","size":147318}],"filteredAssets":0,"assetsSize":174551,"filteredAuxiliaryAssets":1,"auxiliaryAssetsSize":556831}},"assetsByChunkName":{"app":["webpack-runtime-70c10d1287d3421d6317.js","framework-106eaf75e588fec2b76f.js","app-471009a47af3571792ef.js"],"component---src-pages-index-js":["styles.61e7f43be944aab70bb1.css","component---src-pages-index-js-6ea60e05fc2bfc306125.js"]},"childAssetsByChunkName":{}}